createzopecoverage
