Metadata-Version: 1.0
Name: createzopecoverage
Version: 1.5
Summary: Provides single script to create coverage reports
Home-page: http://pypi.python.org/pypi/createzopecoverage
Author: Reinout van Rees
Author-email: reinout@vanrees.org
License: BSD
Platform: UNKNOWN
